Workbook

Sheet Read Me
A1: Vyta Distress Scorecard – v2
A2: Updated 9 October 2026 with feedback from Patrick (Elevon). For use in the Vyta prototype build.
A4: What changed from v1
A5: • The scorecard now produces TWO scores instead of one: a Distress score (how much trouble now) and a Viability score (would the business make money if the cash problem were fixed). This reflects Patrick's main point: balance sheet issues are symptoms, and a profitable business with legacy debt can usually be saved.
A6: • New distress indicators: bank debt growth, facility utilisation, trade creditors split from ATO and bank, debtor collection trend, 'sales up, cash down', operating cash flow ratio, debt-to-asset ratio.
A7: • New viability indicators: equity ratio, gross margin and trend, overhead vs gross profit, underlying profit margin, revenue trend, pipeline coverage, long-term asset coverage.
A8: • Owner questionnaire added for red flags that never appear in the accounts (statutory demands, customer, competitive advantage).
A9: • Kept from v1: creditor days over 90 (Red), ATO debt rising 3 months in a row (Red), under 3 months of cash runway (Red).
A11: How the scoring works
A12: 1. Each indicator is rated Green, Amber or Red against its thresholds.
A13: 2. Distress points: Red 100, Amber 50, Green 0. Viability points: Green 100, Amber 50, Red 0.
A14: 3. Each score is the weighted average of its indicators (0–100). Indicators with no data are excluded, not counted as zero.
... A29: Thresholds are working assumptions from the v1 draft and Patrick's feedback, not industry-calibrated benchmarks. Outputs are indicative early-warning signals, not an insolvency determination or professional advice.

Sheet Summary
A1: Scorecard Summary
A2: Results for the example business (edit the yellow cells on the indicator sheets to test other scenarios).
A4: Result | B4: Value
A5: Distress score (0–100, higher = worse) | B5: ='Distress Indicators'!O18 -> 68
A6: Viability score (0–100, higher = better) | B6: ='Viability Indicators'!O13 -> 87.5
A7: Statutory demand received? (Yes/No) – from owner | B7: No | C7: Override: an unpaid statutory demand forces Distress = High.
A8: Distress band | B8: =IF(B7="Yes","High",IF(B5>=$B$14,"High",IF(B5>=$B$13,"Moderate","Low"))) -> High
A9: Viability band | B9: =IF(B6>=$B$16,"Strong",IF(B6>=$B$17,"Uncertain","Weak")) -> Strong
A10: Indicative pathway | B10: =INDEX('Outcome Matrix'!$B$5:$D$7,MATCH(B8,'Outcome Matrix'!$A$5:$A$7,0),MATCH(B9,'Outcome Matrix'!$B$4:$D$4,0)) -> RESTRUCTURE CANDIDATE: SBR, VA or safe harbour. Profitable business with legacy balance sheet issues. Priority lead for advisory firms.
A12: Band thresholds (editable)
A13: Distress: Moderate from | B13: 30
A14: Distress: High from | B14: 60
A16: Viability: Strong from | B16: 65
A17: Viability: Uncertain from | B17: 40
A19: Indicator count
A20: Distress indicators at Red | B20: =COUNTIF('Distress Indicators'!M5:M17,"Red") -> 5
A21: Distress indicators at Amber | B21: =COUNTIF('Distress Indicators'!M5:M17,"Amber") -> 6
A22: Viability indicators at Red | B22: =COUNTIF('Viability Indicators'!M5:M12,"Red") -> 0
A23: Viability indicators at Amber | B23: =COUNTIF('Viability Indicators'!M5:M12,"Amber") -> 2
A25: Example business: a profitable operator (42% gross margin, 9% underlying margin, revenue +12%) with ATO debt rising 4 months running, tight liquidity and under 3 months of cash. This is the profile Patrick says is worth saving.

Sheet Distress Indicators
A1: Distress Indicators
A2: How much financial trouble is the business in right now? (from Xero data)
A4: ID | B4: Indicator | C4: What it tells you | D4: Calculation | E4: Xero data source | F4: Direction | G4: Amber at | H4: Red at | I4: Weight | J4: Evidence | K4: Status | L4: Example value | M4: Result | N4: Points | O4: Weighted
A5: D1 | B5: Current ratio | C5: Can short-term assets cover short-term debts? Patrick's 'cashables' test. | D5: Current assets ÷ current liabilities | E5: Balance Sheet report | F5: Lower is worse | G5: 1.2 | H5: 1 | I5: 8 | J5: Patrick Q1, Q8 | K5: Rick to confirm formula | L5: 0.85 | M5: =IF(L5="","No data",IF(F5="Higher is worse",IF(L5>=H5,"Red",IF(L5>=G5,"Amber","Green")),IF(L5<=H5,"Red",IF(L5<=G5,"Amber","Green")))) -> Red | N5: =IF(M5="Red",100,IF(M5="Amber",50,0)) -> 100 | O5: =IF(M5="No data",0,I5*N5/100) -> 8
A6: D2 | B6: Quick ratio | C6: Same test using only cash and debtors (the truly 'cashable' items). | D6: (Cash + trade debtors) ÷ current liabilities | E6: Balance Sheet report | F6: Lower is worse | G6: 1 | H6: 0.7 | I6: 8 | J6: Patrick Q1, Q2 | K6: Rick to confirm formula | L6: 0.6 | M6: =IF(L6="","No data",IF(F6="Higher is worse",IF(L6>=H6,"Red",IF(L6>=G6,"Amber","Green")),IF(L6<=H6,"Red",IF(L6<=G6,"Amber","Green")))) -> Red | N6: =IF(M6="Red",100,IF(M6="Amber",50,0)) -> 100 | O6: =IF(M6="No data",0,I6*N6/100) -> 8
A7: D3 | B7: Cash runway (months) | C7: How long the cash lasts at the current burn rate. | D7: Cash ÷ average monthly net cash outflow (last 3 months) | E7: Bank transactions / Bank Summary | F7: Lower is worse | G7: 6 | H7: 3 | I7: 10 | J7: Original draft | K7: Confirmed (draft threshold) | L7: 2.5 | M7: =IF(L7="","No data",IF(F7="Higher is worse",IF(L7>=H7,"Red",IF(L7>=G7,"Amber","Green")),IF(L7<=H7,"Red",IF(L7<=G7,"Amber","Green")))) -> Red | N7: =IF(M7="Red",100,IF(M7="Amber",50,0)) -> 100 | O7: =IF(M7="No data",0,I7*N7/100) -> 10
A8: D4 | B8: ATO debt: consecutive months rising | C8: ATO arrears are the clearest early symptom of a cash problem. | D8: Count of consecutive month-ends where ATO liabilities (GST, PAYG, ICA) increased | E8: Balance Sheet by month (ATO liability accounts) | F8: Higher is worse | G8: 2 | H8: 3 | I8: 12 | J8: Patrick Q4, Q7; original draft | K8: Threshold to confirm ('ATO definitely') | L8: 4 | M8: =IF(L8="","No data",IF(F8="Higher is worse",IF(L8>=H8,"Red",IF(L8>=G8,"Amber","Green")),IF(L8<=H8,"Red",IF(L8<=G8,"Amber","Green")))) -> Red | N8: =IF(M8="Red",100,IF(M8="Amber",50,0)) -> 100 | O8: =IF(M8="No data",0,I8*N8/100) -> 12
A9: D5 | B9: Bank debt growth (6 months) | C9: Growing debt facilities used to plug cash gaps. | D9: % change in loans + overdraft balances over 6 months | E9: Balance Sheet by month (loan/overdraft accounts) | F9: Higher is worse | G9: 0.1 | H9: 0.25 | I9: 7 | J9: Patrick Q2, Q4, Q7 | K9: New from Patrick | L9: 0.18 | M9: =IF(L9="","No data",IF(F9="Higher is worse",IF(L9>=H9,"Red",IF(L9>=G9,"Amber","Green")),IF(L9<=H9,"Red",IF(L9<=G9,"Amber","Green")))) -> Amber | N9: =IF(M9="Red",100,IF(M9="Amber",50,0)) -> 50 | O9: =IF(M9="No data",0,I9*N9/100) -> 3.5
A10: D6 | B10: Facility utilisation | C10: Extended or maxed-out bank limits. | D10: Overdraft/facility drawn ÷ approved limit | E10: Balance from Xero; limit entered manually | F10: Higher is worse | G10: 0.85 | H10: 1 | I10: 6 | J10: Patrick Q7 | K10: New from Patrick | L10: 0.95 | M10: =IF(L10="","No data",IF(F10="Higher is worse",IF(L10>=H10,"Red",IF(L10>=G10,"Amber","Green")),IF(L10<=H10,"Red",IF(L10<=G10,"Amber","Green")))) -> Amber | N10: =IF(M10="Red",100,IF(M10="Amber",50,0)) -> 50 | O10: =IF(M10="No data",0,I10*N10/100) -> 3
A11: D7 | B11: Trade creditor days | C11: How slowly suppliers are being paid. | D11: Trade payables ÷ (COGS + operating expenses) × 365 | E11: Aged Payables + P&L | F11: Higher is worse | G11: 60 | H11: 90 | I11: 7 | J11: Patrick Q1; original draft | K11: Confirmed (draft threshold) | L11: 75 | M11: =IF(L11="","No data",IF(F11="Higher is worse",IF(L11>=H11,"Red",IF(L11>=G11,"Amber","Green")),IF(L11<=H11,"Red",IF(L11<=G11,"Amber","Green")))) -> Amber | N11: =IF(M11="Red",100,IF(M11="Amber",50,0)) -> 50 | O11: =IF(M11="No data",0,I11*N11/100) -> 3.5
A12: D8 | B12: Trade creditors >90 days overdue | C12: Creditors well past due, separate from ATO and bank. | D12: Payables >90 days overdue ÷ total trade payables | E12: Aged Payables report | F12: Higher is worse | G12: 0.15 | H12: 0.3 | I12: 7 | J12: Patrick Q1, Q4, Q7 | K12: New from Patrick | L12: 0.22 | M12: =IF(L12="","No data",IF(F12="Higher is worse",IF(L12>=H12,"Red",IF(L12>=G12,"Amber","Green")),IF(L12<=H12,"Red",IF(L12<=G12,"Amber","Green")))) -> Amber | N12: =IF(M12="Red",100,IF(M12="Amber",50,0)) -> 50 | O12: =IF(M12="No data",0,I12*N12/100) -> 3.5
A13: D9 | B13: Debtor days trend (3 months) | C13: A growing collection problem. | D13: Change in debtor days vs 3 months ago | E13: Aged Receivables + P&L | F13: Higher is worse | G13: 10 | H13: 20 | I13: 5 | J13: Patrick Q1 | K13: New from Patrick | L13: 6 | M13: =IF(L13="","No data",IF(F13="Higher is worse",IF(L13>=H13,"Red",IF(L13>=G13,"Amber","Green")),IF(L13<=H13,"Red",IF(L13<=G13,"Amber","Green")))) -> Green | N13: =IF(M13="Red",100,IF(M13="Amber",50,0)) -> 0 | O13: =IF(M13="No data",0,I13*N13/100) -> 0
A14: D10 | B14: Debtors >90 days overdue | C14: Customers not paying, and the question of why. | D14: Receivables >90 days overdue ÷ total receivables | E14: Aged Receivables report | F14: Higher is worse | G14: 0.15 | H14: 0.25 | I14: 5 | J14: Patrick Q1 | K14: New from Patrick | L14: 0.08 | M14: =IF(L14="","No data",IF(F14="Higher is worse",IF(L14>=H14,"Red",IF(L14>=G14,"Amber","Green")),IF(L14<=H14,"Red",IF(L14<=G14,"Amber","Green")))) -> Green | N14: =IF(M14="Red",100,IF(M14="Amber",50,0)) -> 0 | O14: =IF(M14="No data",0,I14*N14/100) -> 0
A15: D11 | B15: Sales up, cash down | C15: Revenue rising while cash falls: cash is leaking somewhere. | D15: Consecutive months where rolling 3-month revenue rose and cash balance fell | E15: P&L by month + Bank balances | F15: Higher is worse | G15: 2 | H15: 3 | I15: 8 | J15: Patrick Q8 | K15: New from Patrick | L15: 3 | M15: =IF(L15="","No data",IF(F15="Higher is worse",IF(L15>=H15,"Red",IF(L15>=G15,"Amber","Green")),IF(L15<=H15,"Red",IF(L15<=G15,"Amber","Green")))) -> Red | N15: =IF(M15="Red",100,IF(M15="Amber",50,0)) -> 100 | O15: =IF(M15="No data",0,I15*N15/100) -> 8
A16: D12 | B16: Operating cash flow ratio | C16: Is the business generating enough cash from operations to meet short-term debts? | D16: Operating cash flow (last 12 months) ÷ current liabilities | E16: Bank transactions / cash flow derived | F16: Lower is worse | G16: 0.4 | H16: 0.2 | I16: 7 | J16: Patrick Q1 | K16: Rick to confirm formula | L16: 0.25 | M16: =IF(L16="","No data",IF(F16="Higher is worse",IF(L16>=H16,"Red",IF(L16>=G16,"Amber","Green")),IF(L16<=H16,"Red",IF(L16<=G16,"Amber","Green")))) -> Amber | N16: =IF(M16="Red",100,IF(M16="Amber",50,0)) -> 50 | O16: =IF(M16="No data",0,I16*N16/100) -> 3.5
A17: D13 | B17: Debt-to-asset ratio | C17: How much of the business is funded by debt. | D17: Total liabilities ÷ total assets | E17: Balance Sheet report | F17: Higher is worse | G17: 0.7 | H17: 1 | I17: 10 | J17: Patrick Q1, Q8 | K17: New from Patrick | L17: 0.82 | M17: =IF(L17="","No data",IF(F17="Higher is worse",IF(L17>=H17,"Red",IF(L17>=G17,"Amber","Green")),IF(L17<=H17,"Red",IF(L17<=G17,"Amber","Green")))) -> Amber | N17: =IF(M17="Red",100,IF(M17="Amber",50,0)) -> 50 | O17: =IF(M17="No data",0,I17*N17/100) -> 5
H18: Total weight | I18: =SUM(I5:I17) -> 100 | J18: =IF(I18=100,"OK – sums to 100","Check – should sum to 100") -> OK – sums to 100 | N18: Score | O18: =IFERROR(SUM(O5:O17)/SUMPRODUCT((M5:M17<>"No data")*I5:I17)*100,0) -> 68
A20: Direction: 'Higher is worse' turns Amber/Red when the value is at or above the threshold; 'Lower is worse' when at or below. Blank example value = 'No data' and is excluded from the score.
A21: Points: Red 100 / Amber 50 / Green 0 (higher score = more distress).

Sheet Viability Indicators
A1: Viability Indicators
A2: If the cash problem were fixed, would the business make money? (Patrick's core test)
A4: ID | B4: Indicator | C4: What it tells you | D4: Calculation | E4: Xero data source | F4: Direction | G4: Amber at | H4: Red at | I4: Weight | J4: Evidence | K4: Status | L4: Example value | M4: Result | N4: Points | O4: Weighted
A5: V1 | B5: Equity ratio | C5: Is there any value left in the business? | D5: Net assets ÷ total assets | E5: Balance Sheet report | F5: Lower is worse | G5: 0.2 | H5: 0 | I5: 15 | J5: Patrick Q1 | K5: New from Patrick | L5: 0.18 | M5: =IF(L5="","No data",IF(F5="Higher is worse",IF(L5>=H5,"Red",IF(L5>=G5,"Amber","Green")),IF(L5<=H5,"Red",IF(L5<=G5,"Amber","Green")))) -> Amber | N5: =IF(M5="Green",100,IF(M5="Amber",50,0)) -> 50 | O5: =IF(M5="No data",0,I5*N5/100) -> 7.5
A6: V2 | B6: Gross margin | C6: Is there enough margin to fund overheads and fix the balance sheet? | D6: Gross profit ÷ revenue (last 12 months) | E6: P&L report | F6: Lower is worse | G6: 0.3 | H6: 0.15 | I6: 15 | J6: Patrick Q5, Q6 | K6: Threshold varies by industry | L6: 0.42 | M6: =IF(L6="","No data",IF(F6="Higher is worse",IF(L6>=H6,"Red",IF(L6>=G6,"Amber","Green")),IF(L6<=H6,"Red",IF(L6<=G6,"Amber","Green")))) -> Green | N6: =IF(M6="Green",100,IF(M6="Amber",50,0)) -> 100 | O6: =IF(M6="No data",0,I6*N6/100) -> 15
A7: V3 | B7: Gross margin trend (12 months) | C7: Is margin improving or eroding? | D7: Gross margin now minus gross margin 12 months ago (percentage points) | E7: P&L by month | F7: Lower is worse | G7: -0.02 | H7: -0.05 | I7: 10 | J7: Patrick Q5 | K7: New from Patrick | L7: 0.01 | M7: =IF(L7="","No data",IF(F7="Higher is worse",IF(L7>=H7,"Red",IF(L7>=G7,"Amber","Green")),IF(L7<=H7,"Red",IF(L7<=G7,"Amber","Green")))) -> Green | N7: =IF(M7="Green",100,IF(M7="Amber",50,0)) -> 100 | O7: =IF(M7="No data",0,I7*N7/100) -> 10
A8: V4 | B8: Overhead ÷ gross profit | C8: Is the overhead too big for the operation? Could it survive smaller? | D8: Operating expenses ÷ gross profit | E8: P&L report | F8: Higher is worse | G8: 0.9 | H8: 1 | I8: 15 | J8: Patrick Q4, Q5 | K8: New from Patrick | L8: 0.88 | M8: =IF(L8="","No data",IF(F8="Higher is worse",IF(L8>=H8,"Red",IF(L8>=G8,"Amber","Green")),IF(L8<=H8,"Red",IF(L8<=G8,"Amber","Green")))) -> Green | N8: =IF(M8="Green",100,IF(M8="Amber",50,0)) -> 100 | O8: =IF(M8="No data",0,I8*N8/100) -> 15
A9: V5 | B9: Underlying profit margin | C9: 'If I fixed the cash problem, does the business make money?' | D9: (Net profit + interest + depreciation + one-off/legacy costs) ÷ revenue | E9: P&L report (adjustments flagged manually) | F9: Lower is worse | G9: 0.05 | H9: 0 | I9: 20 | J9: Patrick Q1, Q3, Q5 | K9: New from Patrick (core test) | L9: 0.09 | M9: =IF(L9="","No data",IF(F9="Higher is worse",IF(L9>=H9,"Red",IF(L9>=G9,"Amber","Green")),IF(L9<=H9,"Red",IF(L9<=G9,"Amber","Green")))) -> Green | N9: =IF(M9="Green",100,IF(M9="Amber",50,0)) -> 100 | O9: =IF(M9="No data",0,I9*N9/100) -> 20
A10: V6 | B10: Revenue trend (12 months) | C10: Is demand growing or shrinking? | D10: % change in rolling 12-month revenue | E10: P&L by month | F10: Lower is worse | G10: -0.05 | H10: -0.15 | I10: 10 | J10: Patrick Q5 | K10: New from Patrick | L10: 0.12 | M10: =IF(L10="","No data",IF(F10="Higher is worse",IF(L10>=H10,"Red",IF(L10>=G10,"Amber","Green")),IF(L10<=H10,"Red",IF(L10<=G10,"Amber","Green")))) -> Green | N10: =IF(M10="Green",100,IF(M10="Amber",50,0)) -> 100 | O10: =IF(M10="No data",0,I10*N10/100) -> 10
A11: V7 | B11: Pipeline coverage | C11: Lead indicator: what does the order book look like? | D11: Open quotes value ÷ average monthly revenue | E11: Xero Quotes (often incomplete) | F11: Lower is worse | G11: 1 | H11: 0.5 | I11: 5 | J11: Patrick Q2 | K11: New from Patrick (data often patchy) | L11: 1.4 | M11: =IF(L11="","No data",IF(F11="Higher is worse",IF(L11>=H11,"Red",IF(L11>=G11,"Amber","Green")),IF(L11<=H11,"Red",IF(L11<=G11,"Amber","Green")))) -> Green | N11: =IF(M11="Green",100,IF(M11="Amber",50,0)) -> 100 | O11: =IF(M11="No data",0,I11*N11/100) -> 5
A12: V8 | B12: Long-term asset coverage | C12: Asset backing for funders: strong asset coverage = fundable. | D12: Non-current assets ÷ non-current liabilities | E12: Balance Sheet report | F12: Lower is worse | G12: 1.2 | H12: 1 | I12: 10 | J12: Patrick Q8 | K12: New from Patrick | L12: 1.1 | M12: =IF(L12="","No data",IF(F12="Higher is worse",IF(L12>=H12,"Red",IF(L12>=G12,"Amber","Green")),IF(L12<=H12,"Red",IF(L12<=G12,"Amber","Green")))) -> Amber | N12: =IF(M12="Green",100,IF(M12="Amber",50,0)) -> 50 | O12: =IF(M12="No data",0,I12*N12/100) -> 5
H13: Total weight | I13: =SUM(I5:I12) -> 100 | J13: =IF(I13=100,"OK – sums to 100","Check – should sum to 100") -> OK – sums to 100 | N13: Score | O13: =IFERROR(SUM(O5:O12)/SUMPRODUCT((M5:M12<>"No data")*I5:I12)*100,0) -> 87.5
A15: Direction: 'Higher is worse' turns Amber/Red when the value is at or above the threshold; 'Lower is worse' when at or below. Blank example value = 'No data' and is excluded from the score.
A16: Points: Green 100 / Amber 50 / Red 0 (higher score = more viable).

Sheet Outcome Matrix
A1: Outcome Matrix
A2: Distress band × Viability band → indicative pathway. Indicative only, not an insolvency determination.
A4: Distress ↓ / Viability → | B4: Strong | C4: Uncertain | D4: Weak
A5: Low | B5: Healthy. Monitor quarterly. | C5: Performance review: margin, pricing and overhead improvements. | D5: Structural concern: fix the business model before cash runs out.
A6: Moderate | B6: Early intervention: working capital fix, refinance, ATO payment plan. | C6: Turnaround review: where has the cash been going? | D6: Serious: restructure or plan an orderly exit.
A7: High | B7: RESTRUCTURE CANDIDATE: SBR, VA or safe harbour. Profitable business with legacy balance sheet issues. Priority lead for advisory firms. | C7: Urgent advice: assess restructure vs liquidation. | D7: Likely liquidation / exit pathway (CVL, sale of business).
A9: Why two scores: Patrick's view is that balance sheet problems are symptoms. 'A business that is profitable but has legacy balance sheet issues is usually a business that can be saved.' (Q5)

Sheet Owner Questions
A1: Owner Questions
A2: Red flags that never show up in Xero. Asked of the owner (or their advisor) alongside the data scores.
A4: # | B4: Question | C4: Why it matters | D4: Feeds into | E4: Source
A5: 1 | B5: Has the business received a statutory demand (or legal letter of demand) in the last 6 months? | C5: An unpaid statutory demand is a formal insolvency trigger. Overrides the distress band. | D5: Distress (override) | E5: Patrick Q1
A6: 2 | B6: Is the business behind on any bank loan repayments, or has the bank extended or increased limits recently? | C6: Bank arrears and extended limits were key signals Patrick taught bankers to watch. | D6: Distress | E6: Patrick Q7
A7: 3 | B7: Is there an ATO payment plan in place, and is it being met? | C7: Separates managed ATO debt from unmanaged arrears. | D7: Distress | E7: Patrick Q4, Q7
A8: 4 | B8: Who is your customer, and what problem do you solve for them? | C8: No clear customer and problem = no underlying business to save. | D8: Viability | E8: Patrick Q6
A9: 5 | B9: What is your sustainable competitive advantage? If you don't have one, could you get one? | C9: Patrick's core test for whether a business is worth backing. | D9: Viability | E9: Patrick Q6
A10: 6 | B10: If the cash problem were fixed tomorrow, would the business make money? Why? | C10: The owner's view on underlying profitability, tested against V5. | D10: Viability | E10: Patrick Q1, Q5
A11: 7 | B11: Where has the cash been going over the last 12 months? | C11: Balance sheet issues are symptoms. Need to understand the cause. | D11: Both | E11: Patrick Q3
A12: 8 | B12: Could the business operate with a smaller overhead? What would you cut? | C12: Tests the overhead lever (V4). | D12: Viability | E12: Patrick Q4
A13: 9 | B13: What does the pipeline, work in progress or order book look like for the next 3 months? | C13: Lead indicator often missing from Xero. | D13: Viability | E13: Patrick Q2
A14: 10 | B14: Is the business capital-intensive with thin margins, or carrying a large fixed overhead? | C14: Patrick: stay away from businesses that can't make money regardless of what you do. | D14: Viability | E14: Patrick Q6

Sheet Open Items
A1: Open Items
A2: Follow-up with Patrick and Rick before locking v3.
A4: # | B4: Item | C4: Who | D4: Affects | E4: Status
A5: 1 | B5: Preferred short-term liquidity formula (current vs quick ratio, and what counts as 'cashable') | C5: Rick | D5: D1, D2 | E5: Open
A6: 2 | B6: Cash flow ratio formula Rick uses | C6: Rick | D6: D12 | E6: Open
A7: 3 | B7: Which balance sheet movements Rick looks for ('Rick has some gold here') | C7: Rick | D7: New indicators | E7: Open
A8: 4 | B8: Industry ratio benchmarks Rick used for businesses he oversaw | C8: Rick | D8: All thresholds, especially V2 | E8: Open
A9: 5 | B9: Put the 'profitable but legacy balance sheet issues' test into words / a formula | C9: Rick | D9: V5, Outcome Matrix | E9: Open
A10: 6 | B10: 'ATO definitely' (Q4): is the 3-months-rising ATO threshold too harsh or too soft? | C10: Patrick | D10: D4 | E10: Open
A11: 7 | B11: Q8 commercial question: would Elevon pay to see flagged businesses early, and roughly how much? | C11: Patrick | D11: Business model | E11: Open
A12: 8 | B12: Large sporting sponsorships by non-national companies as a red flag | C12: Patrick | D12: Parked – not built | E12: Parked
